{"item_id":107630601,"name":"心动小狐娘","group_id":46,"group_name":"心动小狐娘","part_id":6,"state":"active","properties":{"desc":"画师：siao柒授权~本套装包含动态卡片和超Q表情包，永久购买还能成为认证粉丝，领取粉丝专属装扮！","fan_id":"107630601","fan_item_ids":"1678951878001,1678951924001,1678952088001,1678951836002","fan_mid":"3493080047029111","fan_share_image":"https://i0.hdslb.com/bfs/garb/84fb0879bfc2b9c5f2f10baa70ddb0e7c22ed8d4.png","gray_rule":"true","gray_rule_type":"all","image_cover":"https://i0.hdslb.com/bfs/garb/6e11e50c9c3c7466079cf6a09cd0d189565e9f53.jpg","image_cover_color":"#C4B5BB","item_id_card":"1678951836001","item_id_emoji_package":"1678950985001","item_stock_surplus":"0","owner_uid":"3493080047029111","rank_investor_show":"false","sale_bp_forever_raw":"2500","sale_bp_pm_raw":"600","sale_buy_num_limit":"99","sale_quantity":"20000","sale_quantity_limit":"true","sale_region_ip_limit":"大陆地区","sale_reserve_switch":"true","sale_sku_id_1":"1076306012","sale_sku_id_2":"1076306011","sale_time_begin":"1679563030","sale_time_end":"1711036800","sale_type":"pay","suit_card_type":"big_img","type":"ip"},"current_activity":null,"next_activity":{"type":"open_platform_vip_discount","time_limit":true,"time_left":0,"tag":"大会员平台折扣","price_bp_month":480,"price_bp_forever":2000,"type_month":"open_platform_vip_discount","tag_month":"大会员平台折扣","time_limit_month":true,"time_left_month":0},"current_sources":null,"finish_sources":null,"sale_left_time":0,"sale_time_end":0,"sale_surplus":0,"sale_count_desc":"","total_count_desc":"","tag":"","jump_link":"","sales_mode":0,"suit_items":{"card":[{"item_id":1678951836002,"name":"心动小狐娘粉丝","state":"active","tab_id":0,"suit_item_id":107630601,"properties":{"fan_no_color":"#F3677A","fans_image":"https://i0.hdslb.com/bfs/garb/12266f0ec8e0a0c209dd2aa34824a0d2603d3115.png","fans_material_id":"1678951836002","goods_type":"suit","hot":"false","image":"https://i0.hdslb.com/bfs/garb/12266f0ec8e0a0c209dd2aa34824a0d2603d3115.png","image_preview_small":"https://i0.hdslb.com/bfs/garb/23361d8514135560448ea6b7dd63b09e59fda5f7.png","sale_type":"other"},"current_activity":null,"next_activity":null,"current_sources":null,"finish_sources":null,"sale_left_time":0,"sale_time_end":0,"sale_surplus":0,"items":null},{"item_id":1678951836001,"name":"心动小狐娘","state":"active","tab_id":0,"suit_item_id":107630601,"properties":{"fan_no_color":"#F3677A","fans_image":"https://i0.hdslb.com/bfs/garb/12266f0ec8e0a0c209dd2aa34824a0d2603d3115.png","fans_material_id":"1678951836002","goods_type":"suit","hot":"false","image":"https://i0.hdslb.com/bfs/garb/e3abf95a05e10e53d78d7eb18a062095a2c85be8.png","sale_type":"other"},"current_activity":null,"next_activity":null,"current_sources":null,"finish_sources":null,"sale_left_time":0,"sale_time_end":0,"sale_surplus":0,"items":null}],"card_bg":[{"item_id":1678951924001,"name":"心动小狐娘","state":"active","tab_id":0,"suit_item_id":107630601,"properties":{"fan_no_color":"#E87D8C","goods_type":"suit","image":"https://i0.hdslb.com/bfs/baselabs/op/0b7939ac3aacb4a47e7f8f276a541e862a5ff39d6dd6689c265dbc889cb08839.png","image_preview_small":"https://i0.hdslb.com/bfs/garb/e980323ae59a616c1fb6f82b2b2195eeb31f79fa.png","sale_type":"suit"},"current_activity":null,"next_activity":null,"current_sources":null,"finish_sources":null,"sale_left_time":0,"sale_time_end":0,"sale_surplus":0,"items":null}],"emoji_package":[{"item_id":1678950985001,"name":"心动小狐娘","state":"active","tab_id":0,"suit_item_id":107630601,"properties":{"addable":"true","biz":"reply,dynamic,watch_full","goods_type":"suit","image":"https://i0.hdslb.com/bfs/garb/5ad9c454399ee99a59d8af98fc023e748aadf320.png","is_symbol":"false","item_emoji_list":"[{\"name\":\"棒\",\"image\":\"https://i0.hdslb.com/bfs/garb/eb07c5be32fb99a10e944873878ff6cad1543f10.png\"},{\"name\":\"不行\",\"image\":\"https://i0.hdslb.com/bfs/garb/b9dd8a3f40af17ebe2550554424480de583dedb7.png\"},{\"name\":\"吃瓜\",\"image\":\"https://i0.hdslb.com/bfs/garb/6eb1b65f5bcb197893ae1200878942d273710feb.png\"},{\"name\":\"干杯\",\"image\":\"https://i0.hdslb.com/bfs/garb/2e2bd8d90702183f428d2edb747db87616ec9245.png\"},{\"name\":\"告白\",\"image\":\"https://i0.hdslb.com/bfs/garb/451a78995dcb18ebea661d51e5f1f08ee2b6955a.png\"},{\"name\":\"哈喽\",\"image\":\"https://i0.hdslb.com/bfs/garb/00535548f54779257e58100699fe65c5def451c8.png\"},{\"name\":\"好的\",\"image\":\"https://i0.hdslb.com/bfs/garb/c80296e142ac6050dad066580b2aadb9a48b4336.png\"},{\"name\":\"记仇\",\"image\":\"https://i0.hdslb.com/bfs/garb/3ea169d84c5cd5d0f2b13fe5160f2b0c4c72018b.png\"},{\"name\":\"加油\",\"image\":\"https://i0.hdslb.com/bfs/garb/ca124a7a37c881d4107b8826091fa56978d0b390.png\"},{\"name\":\"哭哭\",\"image\":\"https://i0.hdslb.com/bfs/garb/c54e137707d32345ed97b27dc7421f508fb05844.png\"},{\"name\":\"冷漠\",\"image\":\"https://i0.hdslb.com/bfs/garb/ee7d107caa084d285739dcfd99504ee9c1a577a1.png\"},{\"name\":\"略略\",\"image\":\"https://i0.hdslb.com/bfs/garb/b1470515adb10a22fa78ffdd2b5e35789ff2ee9a.png\"},{\"name\":\"纳尼\",\"image\":\"https://i0.hdslb.com/bfs/garb/562be2b071b3d9b6ff14da71506dc7c4a4c0692a.png\"},{\"name\":\"思考\",\"image\":\"https://i0.hdslb.com/bfs/garb/ce86d34c36393897d3ab70c1b718f76a2e0775c5.png\"},{\"name\":\"偷看\",\"image\":\"https://i0.hdslb.com/bfs/garb/2213552efd8399274e0e74d42add16f9eaa85bf5.png\"}]","permanent":"false","preview":"false","recently_used":"false","recommend":"false","removable":"true","sale_type":"pay","setting_pannel_not_show":"false","size":"L","sortable":"true"},"current_activity":null,"next_activity":null,"current_sources":null,"finish_sources":null,"sale_left_time":0,"sale_time_end":0,"sale_surplus":0,"items":[{"item_id":0,"name":"[心动小狐娘_棒]","state":"active","tab_id":0,"suit_item_id":0,"properties":{"image":"https://i0.hdslb.com/bfs/garb/eb07c5be32fb99a10e944873878ff6cad1543f10.png","sale_type":"pay"},"current_activity":null,"next_activity":null,"current_sources":null,"finish_sources":null,"sale_left_time":0,"sale_time_end":0,"sale_surplus":0},{"item_id":0,"name":"[心动小狐娘_不行]","state":"active","tab_id":0,"suit_item_id":0,"properties":{"image":"https://i0.hdslb.com/bfs/garb/b9dd8a3f40af17ebe2550554424480de583dedb7.png","sale_type":"pay"},"current_activity":null,"next_activity":null,"current_sources":null,"finish_sources":null,"sale_left_time":0,"sale_time_end":0,"sale_surplus":0},{"item_id":0,"name":"[心动小狐娘_吃瓜]","state":"active","tab_id":0,"suit_item_id":0,"properties":{"image":"https://i0.hdslb.com/bfs/garb/6eb1b65f5bcb197893ae1200878942d273710feb.png","sale_type":"pay"},"current_activity":null,"next_activity":null,"current_sources":null,"finish_sources":null,"sale_left_time":0,"sale_time_end":0,"sale_surplus":0},{"item_id":0,"name":"[心动小狐娘_干杯]","state":"active","tab_id":0,"suit_item_id":0,"properties":{"image":"https://i0.hdslb.com/bfs/garb/2e2bd8d90702183f428d2edb747db87616ec9245.png","sale_type":"pay"},"current_activity":null,"next_activity":null,"current_sources":null,"finish_sources":null,"sale_left_time":0,"sale_time_end":0,"sale_surplus":0},{"item_id":0,"name":"[心动小狐娘_告白]","state":"active","tab_id":0,"suit_item_id":0,"properties":{"image":"https://i0.hdslb.com/bfs/garb/451a78995dcb18ebea661d51e5f1f08ee2b6955a.png","sale_type":"pay"},"current_activity":null,"next_activity":null,"current_sources":null,"finish_sources":null,"sale_left_time":0,"sale_time_end":0,"sale_surplus":0},{"item_id":0,"name":"[心动小狐娘_哈喽]","state":"active","tab_id":0,"suit_item_id":0,"properties":{"image":"https://i0.hdslb.com/bfs/garb/00535548f54779257e58100699fe65c5def451c8.png","sale_type":"pay"},"current_activity":null,"next_activity":null,"current_sources":null,"finish_sources":null,"sale_left_time":0,"sale_time_end":0,"sale_surplus":0},{"item_id":0,"name":"[心动小狐娘_好的]","state":"active","tab_id":0,"suit_item_id":0,"properties":{"image":"https://i0.hdslb.com/bfs/garb/c80296e142ac6050dad066580b2aadb9a48b4336.png","sale_type":"pay"},"current_activity":null,"next_activity":null,"current_sources":null,"finish_sources":null,"sale_left_time":0,"sale_time_end":0,"sale_surplus":0},{"item_id":0,"name":"[心动小狐娘_记仇]","state":"active","tab_id":0,"suit_item_id":0,"properties":{"image":"https://i0.hdslb.com/bfs/garb/3ea169d84c5cd5d0f2b13fe5160f2b0c4c72018b.png","sale_type":"pay"},"current_activity":null,"next_activity":null,"current_sources":null,"finish_sources":null,"sale_left_time":0,"sale_time_end":0,"sale_surplus":0},{"item_id":0,"name":"[心动小狐娘_加油]","state":"active","tab_id":0,"suit_item_id":0,"properties":{"image":"https://i0.hdslb.com/bfs/garb/ca124a7a37c881d4107b8826091fa56978d0b390.png","sale_type":"pay"},"current_activity":null,"next_activity":null,"current_sources":null,"finish_sources":null,"sale_left_time":0,"sale_time_end":0,"sale_surplus":0},{"item_id":0,"name":"[心动小狐娘_哭哭]","state":"active","tab_id":0,"suit_item_id":0,"properties":{"image":"https://i0.hdslb.com/bfs/garb/c54e137707d32345ed97b27dc7421f508fb05844.png","sale_type":"pay"},"current_activity":null,"next_activity":null,"current_sources":null,"finish_sources":null,"sale_left_time":0,"sale_time_end":0,"sale_surplus":0},{"item_id":0,"name":"[心动小狐娘_冷漠]","state":"active","tab_id":0,"suit_item_id":0,"properties":{"image":"https://i0.hdslb.com/bfs/garb/ee7d107caa084d285739dcfd99504ee9c1a577a1.png","sale_type":"pay"},"current_activity":null,"next_activity":null,"current_sources":null,"finish_sources":null,"sale_left_time":0,"sale_time_end":0,"sale_surplus":0},{"item_id":0,"name":"[心动小狐娘_略略]","state":"active","tab_id":0,"suit_item_id":0,"properties":{"image":"https://i0.hdslb.com/bfs/garb/b1470515adb10a22fa78ffdd2b5e35789ff2ee9a.png","sale_type":"pay"},"current_activity":null,"next_activity":null,"current_sources":null,"finish_sources":null,"sale_left_time":0,"sale_time_end":0,"sale_surplus":0},{"item_id":0,"name":"[心动小狐娘_纳尼]","state":"active","tab_id":0,"suit_item_id":0,"properties":{"image":"https://i0.hdslb.com/bfs/garb/562be2b071b3d9b6ff14da71506dc7c4a4c0692a.png","sale_type":"pay"},"current_activity":null,"next_activity":null,"current_sources":null,"finish_sources":null,"sale_left_time":0,"sale_time_end":0,"sale_surplus":0},{"item_id":0,"name":"[心动小狐娘_思考]","state":"active","tab_id":0,"suit_item_id":0,"properties":{"image":"https://i0.hdslb.com/bfs/garb/ce86d34c36393897d3ab70c1b718f76a2e0775c5.png","sale_type":"pay"},"current_activity":null,"next_activity":null,"current_sources":null,"finish_sources":null,"sale_left_time":0,"sale_time_end":0,"sale_surplus":0},{"item_id":0,"name":"[心动小狐娘_偷看]","state":"active","tab_id":0,"suit_item_id":0,"properties":{"image":"https://i0.hdslb.com/bfs/garb/2213552efd8399274e0e74d42add16f9eaa85bf5.png","sale_type":"pay"},"current_activity":null,"next_activity":null,"current_sources":null,"finish_sources":null,"sale_left_time":0,"sale_time_end":0,"sale_surplus":0}]}],"skin":[{"item_id":1678952088001,"name":"心动小狐娘","state":"active","tab_id":0,"suit_item_id":107630601,"properties":{"color":"#ffffff","color_mode":"dark","color_second_page":"#2D2B40","goods_type":"suit","head_bg":"https://i0.hdslb.com/bfs/garb/ad9d90af1fbe96c41d769f9e168cacf501dee929.png","head_myself_mp4_bg":"","head_myself_mp4_play":"loop","head_myself_squared_bg":"https://i0.hdslb.com/bfs/garb/d80985cb8916f6e451d22eac61a92b2049301a85.jpg","head_tab_bg":"https://i0.hdslb.com/bfs/baselabs/op/4cc55ec51e452688ab54a3dfe3865ed7959fe715ce5db2c7d0660d1fc1991b56.png","image_cover":"https://i0.hdslb.com/bfs/garb/4e7648eac688f2e19ef2db0a7d3751232bbe4885.jpg","image_preview":"https://i0.hdslb.com/bfs/garb/4e7648eac688f2e19ef2db0a7d3751232bbe4885.jpg","package_md5":"49f504868e27f812ce59179174071b58","package_url":"https://i0.hdslb.com/bfs/garb/zip/42c27a9db7acc509c2cf9a87138f33d7a66baa9a.zip","tail_bg":"https://i0.hdslb.com/bfs/garb/dcf9cb0e7d41283655bed75a2b9e0ae4efd80bc0.png","tail_color":"#AACADD","tail_color_selected":"#EBF7FF","tail_icon_channel":"https://i0.hdslb.com/bfs/garb/52f3536ef83e94294af20844be3878e8682a0753.png","tail_icon_dynamic":"https://i0.hdslb.com/bfs/garb/52f3536ef83e94294af20844be3878e8682a0753.png","tail_icon_main":"https://i0.hdslb.com/bfs/garb/71fe173baf8f5b76ba5a5b59dfe8300b7206cb52.png","tail_icon_mode":"img","tail_icon_myself":"https://i0.hdslb.com/bfs/garb/967f28017d2bc5f65a3c291acd5736320cd0c4e8.png","tail_icon_pub_btn_bg":"https://i0.hdslb.com/bfs/garb/cbf8f83145814220b40b4f8b330aced803bf70d4.png","tail_icon_selected_channel":"https://i0.hdslb.com/bfs/garb/6b62c3d36345378218c9c832b27d7df2865a349e.png","tail_icon_selected_dynamic":"https://i0.hdslb.com/bfs/garb/6b62c3d36345378218c9c832b27d7df2865a349e.png","tail_icon_selected_main":"https://i0.hdslb.com/bfs/garb/518b026dc96746f8f964e4804c7bab0a620790cf.png","tail_icon_selected_myself":"https://i0.hdslb.com/bfs/garb/f3f890ffa16e7b1fd6647798c9f590a1564141dc.png","tail_icon_selected_pub_btn_bg":"https://i0.hdslb.com/bfs/garb/cbf8f83145814220b40b4f8b330aced803bf70d4.png","tail_icon_selected_shop":"https://i0.hdslb.com/bfs/garb/b89e7d5d193dfbfc6ac35db44ffc9a072accb013.png","tail_icon_shop":"https://i0.hdslb.com/bfs/garb/d333d9992df4db6437dafbb1cc3441928ea258ee.png","ver":"1679019145"},"current_activity":null,"next_activity":null,"current_sources":null,"finish_sources":null,"sale_left_time":0,"sale_time_end":0,"sale_surplus":0,"items":null}],"space_bg":[{"item_id":1678951878001,"name":"心动小狐娘","state":"active","tab_id":0,"suit_item_id":107630601,"properties":{"fan_no_color":"#ffffff","goods_type":"suit","image1_landscape":"https://i0.hdslb.com/bfs/garb/b917ec359490be3e66bf1ff25e5f31990bb9f28c.jpg","image1_portrait":"https://i0.hdslb.com/bfs/garb/f4f46324588f9df1a3b28759d4657d154476a93b.jpg"},"current_activity":null,"next_activity":null,"current_sources":null,"finish_sources":null,"sale_left_time":0,"sale_time_end":0,"sale_surplus":0,"items":null}]},"fan_user":{"mid":3493080047029111,"nickname":"奶物联萌","avatar":"https://i1.hdslb.com/bfs/face/f5081533c9599cecafd532501a99ff088ac786b3.jpg"},"unlock_items":null,"activity_entrance":{"id":0,"item_id":0,"title":"","image_cover":"","jump_link":""}}