{
	"item_id":206751301,
	"name":"花·兔兔·爱丽丝",
	"group_id":46,
	"group_name":"花·兔兔·爱丽丝",
	"part_id":6,
	"properties":{
		"desc":"欢迎来到爱丽丝的小花园~本套装预留编号：1-5-9.",
		"fan_id":"206751301",
		"fan_item_ids":"1709800263002,1709800470001,1709801367001,1709802039001",
		"fan_mid":"15938156",
		"fan_share_image":"https://i0.hdslb.com/bfs/garb/603e0f1c45c5ab65405374e4e58286f68ced379f.png",
		"image_cover":"https://i0.hdslb.com/bfs/garb/4858b82d21eaabddb6a5016ca80972e1a4099fa6.jpg",
		"image_cover_color":"#FEF7EB",
		"item_id_card":"1709800263001",
		"item_id_emoji_package":"1709800351001",
		"owner_uid":"15938156",
		"rank_investor_show":"false",
		"sale_bp_forever_raw":"2500",
		"sale_bp_pm_raw":"600",
		"sale_buy_num_limit":"99",
		"sale_quantity":"5000",
		"sale_quantity_limit":"true",
		"sale_region_ip_limit":"全球",
		"sale_reserve_switch":"true",
		"sale_sku_id_1":"2067513012",
		"sale_sku_id_2":"2067513011",
		"sale_time_begin":"1709978400",
		"sale_type":"pay",
		"suit_card_type":"big_img",
		"type":"ip"
	},
	"suit_items":{
		"card":[
			{
				"item_id":1709800263001,
				"name":"花·兔兔·爱丽丝",
				"tab_id":0,
				"suit_item_id":206751301,
				"properties":{
					"fan_no_color":"#A2AF3D",
					"fans_image":"https://i0.hdslb.com/bfs/garb/a60901fe9ea23edb0bcd28d1c2a5fa8e6f470ba3.png",
					"fans_material_id":"1709800263002",
					"goods_type":"suit",
					"image":"https://i0.hdslb.com/bfs/garb/3bf36f92b94efdf33ac0d23243eb08d1320c19a8.png",
					"sale_type":"other"
				}
			},
			{
				"item_id":1709800263002,
				"name":"花·兔兔·爱丽丝粉丝",
				"tab_id":0,
				"suit_item_id":206751301,
				"properties":{
					"fan_no_color":"#A2AF3D",
					"fans_image":"https://i0.hdslb.com/bfs/garb/a60901fe9ea23edb0bcd28d1c2a5fa8e6f470ba3.png",
					"fans_material_id":"1709800263002",
					"goods_type":"suit",
					"image":"https://i0.hdslb.com/bfs/garb/a60901fe9ea23edb0bcd28d1c2a5fa8e6f470ba3.png",
					"image_preview_small":"https://i0.hdslb.com/bfs/garb/4f5c011e94d76da055c194de3c0c0592c612f17c.png",
					"sale_type":"other"
				}
			}
		],
		"card_bg":[
			{
				"item_id":1709802039001,
				"name":"花·兔兔·爱丽丝",
				"tab_id":0,
				"suit_item_id":206751301,
				"properties":{
					"fan_no_color":"#A2AF3D",
					"goods_type":"suit",
					"image":"https://i0.hdslb.com/bfs/baselabs/op/17d1cc4d554de2eb288d25bda506814b880e6f905d4d1d5aa98c52a9a2a7fbff.png",
					"image_preview_small":"https://i0.hdslb.com/bfs/garb/a10b53f109b7b8451fb7011d83fc73818cd2d503.png",
					"sale_type":"suit"
				}
			}
		],
		"emoji_package":[
			{
				"item_id":1709800351001,
				"name":"花·兔兔·爱丽丝",
				"tab_id":0,
				"suit_item_id":206751301,
				"properties":{
					"addable":"true",
					"biz":"reply,dynamic,watch_full",
					"goods_type":"suit",
					"image":"https://i0.hdslb.com/bfs/garb/04ad035682ef0b827d9997327366ba726e3c0d93.png",
					"is_symbol":"false",
					"item_emoji_list":"[{\"name\":\"草莓兔兔\",\"image\":\"https://i0.hdslb.com/bfs/garb/a955eda230bb01b06d79b247f222a2dbda675d4a.png\"},{\"name\":\"下雨天\",\"image\":\"https://i0.hdslb.com/bfs/garb/1204dca532aa6495fc30334a4b9b03a7ba32b003.png\"},{\"name\":\"吓你一跳\",\"image\":\"https://i0.hdslb.com/bfs/garb/099ce8d30da244b14768972ddeb239d017de1ec4.png\"},{\"name\":\"你好呀\",\"image\":\"https://i0.hdslb.com/bfs/garb/1b5c209873b192a0d91db93761d55b10ae823f93.png\"},{\"name\":\"wink\",\"image\":\"https://i0.hdslb.com/bfs/garb/fb09db57f6eac8ede2b8af05e4d95606ffa90b42.png\"},{\"name\":\"送你花花\",\"image\":\"https://i0.hdslb.com/bfs/garb/8d95ae9c9308d1de327f757990b8da759263a4f7.png\"},{\"name\":\"突然出现\",\"image\":\"https://i0.hdslb.com/bfs/garb/323fe9e0078bae3035f538bdb30796a729128d1e.png\"},{\"name\":\"好~\",\"image\":\"https://i0.hdslb.com/bfs/garb/124b48bc26bff5ad2246825e48d02c31cf392532.png\"},{\"name\":\"心花怒放\",\"image\":\"https://i0.hdslb.com/bfs/garb/556717ae5756867541194cfe0a51c4178f4b202e.png\"},{\"name\":\"爱的星球\",\"image\":\"https://i0.hdslb.com/bfs/garb/131e0dc5d2c96e4e76a964b8cc6b5a9ef3d2a71c.png\"},{\"name\":\"跳舞\",\"image\":\"https://i0.hdslb.com/bfs/garb/0bdd4a3a01bc0051ca560f0ac9e6fa646ab63dfc.png\"},{\"name\":\"许愿星\",\"image\":\"https://i0.hdslb.com/bfs/garb/cc29115966825694410c6245107792fc5217b2ee.png\"},{\"name\":\"铃兰猫猫\",\"image\":\"https://i0.hdslb.com/bfs/garb/f9181384437844172bfd1e644d015f5736a7f49b.png\"},{\"name\":\"铃兰修狗\",\"image\":\"https://i0.hdslb.com/bfs/garb/05915784f6947baf289df1ff982380d4bbe423bf.png\"},{\"name\":\"铃兰兔兔\",\"image\":\"https://i0.hdslb.com/bfs/garb/20dc13bbb65239936d8972b99a37813792ead66e.png\"}]",
					"permanent":"false",
					"preview":"false",
					"recently_used":"false",
					"recommend":"false",
					"removable":"true",
					"sale_type":"pay",
					"setting_pannel_not_show":"false",
					"size":"L",
					"sortable":"true"
				},
				"items":[
					{
						"item_id":0,
						"name":"[花·兔兔·爱丽丝_wink]",
						"tab_id":0,
						"properties":{
							"image":"https://i0.hdslb.com/bfs/garb/fb09db57f6eac8ede2b8af05e4d95606ffa90b42.png",
							"sale_type":"pay"
						}
					},
					{
						"item_id":0,
						"name":"[花·兔兔·爱丽丝_下雨天]",
						"tab_id":0,
						"properties":{
							"image":"https://i0.hdslb.com/bfs/garb/1204dca532aa6495fc30334a4b9b03a7ba32b003.png",
							"sale_type":"pay"
						}
					},
					{
						"item_id":0,
						"name":"[花·兔兔·爱丽丝_你好呀]",
						"tab_id":0,
						"properties":{
							"image":"https://i0.hdslb.com/bfs/garb/1b5c209873b192a0d91db93761d55b10ae823f93.png",
							"sale_type":"pay"
						}
					},
					{
						"item_id":0,
						"name":"[花·兔兔·爱丽丝_吓你一跳]",
						"tab_id":0,
						"properties":{
							"image":"https://i0.hdslb.com/bfs/garb/099ce8d30da244b14768972ddeb239d017de1ec4.png",
							"sale_type":"pay"
						}
					},
					{
						"item_id":0,
						"name":"[花·兔兔·爱丽丝_好~]",
						"tab_id":0,
						"properties":{
							"image":"https://i0.hdslb.com/bfs/garb/124b48bc26bff5ad2246825e48d02c31cf392532.png",
							"sale_type":"pay"
						}
					},
					{
						"item_id":0,
						"name":"[花·兔兔·爱丽丝_心花怒放]",
						"tab_id":0,
						"properties":{
							"image":"https://i0.hdslb.com/bfs/garb/556717ae5756867541194cfe0a51c4178f4b202e.png",
							"sale_type":"pay"
						}
					},
					{
						"item_id":0,
						"name":"[花·兔兔·爱丽丝_爱的星球]",
						"tab_id":0,
						"properties":{
							"image":"https://i0.hdslb.com/bfs/garb/131e0dc5d2c96e4e76a964b8cc6b5a9ef3d2a71c.png",
							"sale_type":"pay"
						}
					},
					{
						"item_id":0,
						"name":"[花·兔兔·爱丽丝_突然出现]",
						"tab_id":0,
						"properties":{
							"image":"https://i0.hdslb.com/bfs/garb/323fe9e0078bae3035f538bdb30796a729128d1e.png",
							"sale_type":"pay"
						}
					},
					{
						"item_id":0,
						"name":"[花·兔兔·爱丽丝_草莓兔兔]",
						"tab_id":0,
						"properties":{
							"image":"https://i0.hdslb.com/bfs/garb/a955eda230bb01b06d79b247f222a2dbda675d4a.png",
							"sale_type":"pay"
						}
					},
					{
						"item_id":0,
						"name":"[花·兔兔·爱丽丝_许愿星]",
						"tab_id":0,
						"properties":{
							"image":"https://i0.hdslb.com/bfs/garb/cc29115966825694410c6245107792fc5217b2ee.png",
							"sale_type":"pay"
						}
					},
					{
						"item_id":0,
						"name":"[花·兔兔·爱丽丝_跳舞]",
						"tab_id":0,
						"properties":{
							"image":"https://i0.hdslb.com/bfs/garb/0bdd4a3a01bc0051ca560f0ac9e6fa646ab63dfc.png",
							"sale_type":"pay"
						}
					},
					{
						"item_id":0,
						"name":"[花·兔兔·爱丽丝_送你花花]",
						"tab_id":0,
						"properties":{
							"image":"https://i0.hdslb.com/bfs/garb/8d95ae9c9308d1de327f757990b8da759263a4f7.png",
							"sale_type":"pay"
						}
					},
					{
						"item_id":0,
						"name":"[花·兔兔·爱丽丝_铃兰修狗]",
						"tab_id":0,
						"properties":{
							"image":"https://i0.hdslb.com/bfs/garb/05915784f6947baf289df1ff982380d4bbe423bf.png",
							"sale_type":"pay"
						}
					},
					{
						"item_id":0,
						"name":"[花·兔兔·爱丽丝_铃兰兔兔]",
						"tab_id":0,
						"properties":{
							"image":"https://i0.hdslb.com/bfs/garb/20dc13bbb65239936d8972b99a37813792ead66e.png",
							"sale_type":"pay"
						}
					},
					{
						"item_id":0,
						"name":"[花·兔兔·爱丽丝_铃兰猫猫]",
						"tab_id":0,
						"properties":{
							"image":"https://i0.hdslb.com/bfs/garb/f9181384437844172bfd1e644d015f5736a7f49b.png",
							"sale_type":"pay"
						}
					}
				]
			}
		],
		"skin":[
			{
				"item_id":1709801367001,
				"name":"花·兔兔·爱丽丝",
				"tab_id":0,
				"suit_item_id":206751301,
				"properties":{
					"color":"#000000",
					"color_mode":"light",
					"color_second_page":"#FEF7EB",
					"goods_type":"suit",
					"head_bg":"https://i0.hdslb.com/bfs/garb/f8cb2305e71429bf49090ee5faa7d1d913b31191.jpg",
					"head_myself_mp4_bg":"",
					"head_myself_mp4_play":"loop",
					"head_myself_squared_bg":"https://i0.hdslb.com/bfs/garb/dd8e11e0b960d23366d83820881c0625b69ed6b8.jpg",
					"head_tab_bg":"https://i0.hdslb.com/bfs/baselabs/op/0151efde40fbecb5e58d5032d3b78f187e67dbc0ea9d2fe2c48f882dfb80645f.png",
					"image_cover":"https://i0.hdslb.com/bfs/garb/4858b82d21eaabddb6a5016ca80972e1a4099fa6.jpg",
					"image_preview":"https://i0.hdslb.com/bfs/garb/4858b82d21eaabddb6a5016ca80972e1a4099fa6.jpg",
					"package_md5":"655db317f36fda0625bfc6b4a91e9108",
					"package_url":"https://i0.hdslb.com/bfs/garb/zip/dfdb26351b48e6d8f8159b0523a476ff022c102e.zip",
					"tail_bg":"https://i0.hdslb.com/bfs/garb/cc6cbf66cff97517e42d2a8fc7b33a6785936932.png",
					"tail_color":"#795A56",
					"tail_color_selected":"#A43532",
					"tail_icon_channel":"https://i0.hdslb.com/bfs/garb/79fca51365927cc9a687ee7d123a114dccc2edf5.png",
					"tail_icon_dynamic":"https://i0.hdslb.com/bfs/garb/79fca51365927cc9a687ee7d123a114dccc2edf5.png",
					"tail_icon_main":"https://i0.hdslb.com/bfs/garb/3d5a3b2f5d57b968a5d4cd32771e2976fc99527a.png",
					"tail_icon_mode":"img",
					"tail_icon_myself":"https://i0.hdslb.com/bfs/garb/52eae7e7d71996da9ffd04c4177c795274d551d8.png",
					"tail_icon_pub_btn_bg":"https://i0.hdslb.com/bfs/garb/5cc74fa4395fd0f6a94241d10d78eaad97cdb371.png",
					"tail_icon_selected_channel":"https://i0.hdslb.com/bfs/garb/396961ca38101ede1cdcff8a833f57039258ddac.png",
					"tail_icon_selected_dynamic":"https://i0.hdslb.com/bfs/garb/396961ca38101ede1cdcff8a833f57039258ddac.png",
					"tail_icon_selected_main":"https://i0.hdslb.com/bfs/garb/0816bdd992c1c0f68cdfff1b3ef6901862aad765.png",
					"tail_icon_selected_myself":"https://i0.hdslb.com/bfs/garb/7cdbf4241cbebb50632930512adf26c191fa70d5.png",
					"tail_icon_selected_pub_btn_bg":"https://i0.hdslb.com/bfs/garb/5cc74fa4395fd0f6a94241d10d78eaad97cdb371.png",
					"tail_icon_selected_shop":"https://i0.hdslb.com/bfs/garb/42742cfe7fc6e52417b56236c3d959a45741765c.png",
					"tail_icon_shop":"https://i0.hdslb.com/bfs/garb/000fef81ef752fc7ab7d3a2a67da1cac7e68840e.png",
					"ver":"1709802431"
				}
			}
		],
		"space_bg":[
			{
				"item_id":1709800470001,
				"name":"花·兔兔·爱丽丝",
				"tab_id":0,
				"suit_item_id":206751301,
				"properties":{
					"fan_no_color":"#ffffff",
					"goods_type":"suit",
					"image1_landscape":"https://i0.hdslb.com/bfs/garb/ba83c50d9134c1698ba81eab4851424f3012c7fd.jpg",
					"image1_portrait":"https://i0.hdslb.com/bfs/garb/a0bed3a2d102f2b5b4ddfb69c4affac19870a688.jpg",
					"image2_landscape":"https://i0.hdslb.com/bfs/garb/2d8ea72a8dc67baa208fbd15ac918fd319d186bd.jpg",
					"image2_portrait":"https://i0.hdslb.com/bfs/garb/c43394902687262ba14439c88da2777201dbae27.jpg"
				}
			}
		]
	},
	"fan_user":{
		"mid":15938156,
		"nickname":"卓漫科技",
		"avatar":"https://i2.hdslb.com/bfs/face/9f1f65e93ebce1444f024b48f930d2db02caddae.jpg"
	}
}