{
	"item_id":323130601,
	"name":"绯色下午茶",
	"group_id":46,
	"group_name":"绯色下午茶",
	"part_id":6,
	"properties":{
		"desc":"小熊姐姐邀请你一起喝下午茶啦~预留编号：1,3,6,11,6666",
		"fan_id":"323130601",
		"fan_item_ids":"1755568934002,1755568958001,1755569056001,1755569308001",
		"fan_mid":"3493131766991076",
		"fan_share_image":"https://i0.hdslb.com/bfs/garb/98e0921378e91b2c0ce29fd870ca67e9b3634af9.png",
		"first_up":"1755598362",
		"image_cover":"https://i0.hdslb.com/bfs/garb/36068f27011b4dab8387a1c4d0acdc00d1c00b01.jpg",
		"image_cover_color":"#FFFFFF",
		"item_id_card":"1755568934001",
		"item_id_emoji_package":"1755508805001",
		"owner_uid":"3493131766991076",
		"rank_investor_show":"false",
		"sale_bp_forever_raw":"2500",
		"sale_bp_pm_raw":"600",
		"sale_buy_num_limit":"99",
		"sale_quantity":"9999",
		"sale_quantity_limit":"true",
		"sale_region_ip_limit":"全球",
		"sale_reserve_switch":"true",
		"sale_sku_id_1":"3231306012",
		"sale_sku_id_2":"3231306011",
		"sale_time_begin":"1755922891",
		"sale_type":"pay",
		"suit_card_type":"big_img",
		"type":"ip"
	},
	"suit_items":{
		"card":[
			{
				"item_id":1755568934001,
				"name":"绯色下午茶",
				"suit_item_id":323130601,
				"properties":{
					"fan_no_color":"#AE5D51",
					"fans_image":"https://i0.hdslb.com/bfs/garb/7760b51d59b34bfc667b34dc3fa8355790e648fc.png",
					"fans_material_id":"1755568934002",
					"goods_type":"suit",
					"image":"https://i0.hdslb.com/bfs/garb/ad16cedb26ac20985e62d8f981ab2d81c0233604.png",
					"sale_type":"other"
				}
			},
			{
				"item_id":1755568934002,
				"name":"绯色下午茶粉丝",
				"suit_item_id":323130601,
				"properties":{
					"fan_no_color":"#AE5D51",
					"fans_image":"https://i0.hdslb.com/bfs/garb/7760b51d59b34bfc667b34dc3fa8355790e648fc.png",
					"fans_material_id":"1755568934002",
					"goods_type":"suit",
					"image":"https://i0.hdslb.com/bfs/garb/7760b51d59b34bfc667b34dc3fa8355790e648fc.png",
					"image_preview_small":"https://i0.hdslb.com/bfs/garb/e02f0655c589ed3ad1d4c0871c483db743468210.png",
					"sale_type":"other"
				}
			}
		],
		"card_bg":[
			{
				"item_id":1755568958001,
				"name":"绯色下午茶",
				"suit_item_id":323130601,
				"properties":{
					"fan_no_color":"#AE5D51",
					"goods_type":"suit",
					"image":"https://i0.hdslb.com/bfs/baselabs/op/189ee80bc3802b9f8a219ef26f54bab968fb7bfb183e00fcf85b5830d4cb6a46.png",
					"image_preview_small":"https://i0.hdslb.com/bfs/garb/d8b7f6aae58fd22b28062e8815277a3c5f7eb4d3.png",
					"sale_type":"suit"
				}
			}
		],
		"emoji_package":[
			{
				"item_id":1755508805001,
				"name":"绯色下午茶",
				"suit_item_id":323130601,
				"properties":{
					"addable":"true",
					"biz":"reply,dynamic,watch_full",
					"goods_type":"suit",
					"image":"https://i0.hdslb.com/bfs/garb/c366adff1f354da1797af304c07a1af1f1fc19ba.png",
					"item_emoji_list":"[{\"name\":\"叫我吗\",\"image\":\"https://i0.hdslb.com/bfs/garb/9880537d42433a3acf28b3119acc859c3275ad42.png\"},{\"name\":\"Hi\",\"image\":\"https://i0.hdslb.com/bfs/garb/ed994898a23272f974cb2bdd7ca2c0d813f42fb8.png\"},{\"name\":\"先走咯\",\"image\":\"https://i0.hdslb.com/bfs/garb/150661c0a7aee1a5cfff01a7e121171f824dd93d.png\"},{\"name\":\"撒泼\",\"image\":\"https://i0.hdslb.com/bfs/garb/57335c0718f443d8a90c8bfc743f7555cbcc181d.png\"},{\"name\":\"我给你等着\",\"image\":\"https://i0.hdslb.com/bfs/garb/f982d006ce3ae6e82112b7da26e0dc5d7d036311.png\"},{\"name\":\"好吃\",\"image\":\"https://i0.hdslb.com/bfs/garb/4f4eb9519f03487195adeb52af83a7234cc3a4b9.png\"},{\"name\":\"中\",\"image\":\"https://i0.hdslb.com/bfs/garb/e18037706193234be7a159fa7fce19f8ceaf0149.png\"},{\"name\":\"不乘\",\"image\":\"https://i0.hdslb.com/bfs/garb/d4f597f4277a8ccebcbac0c1926da977cd9d7c27.png\"},{\"name\":\"够了\",\"image\":\"https://i0.hdslb.com/bfs/garb/b6706e87261d49c37c093ab2d94d899d37a1fd48.png\"},{\"name\":\"哭着跑走\",\"image\":\"https://i0.hdslb.com/bfs/garb/0587a3de60caca49e66ac74fe247cda395e64f6a.png\"},{\"name\":\"喜欢\",\"image\":\"https://i0.hdslb.com/bfs/garb/f4fea1f353805dc6eed0de40d06dc4997ac1aa3a.png\"},{\"name\":\"恁咋不早说\",\"image\":\"https://i0.hdslb.com/bfs/garb/514de3c8e8af894df402858a0a822a0739dd617b.png\"},{\"name\":\"不懂\",\"image\":\"https://i0.hdslb.com/bfs/garb/cf2f589278c2af4b5533e4e3e9c9ec564ee3e160.png\"},{\"name\":\"绅士\",\"image\":\"https://i0.hdslb.com/bfs/garb/2e7d14313b878be5d6258a01f2082031d120c134.png\"},{\"name\":\"激动\",\"image\":\"https://i0.hdslb.com/bfs/garb/3def99fd8a9bc57a4209ada8bbde4e56177acc2d.png\"}]",
					"permanent":"false",
					"preview":"false",
					"recently_used":"false",
					"recommend":"false",
					"removable":"true",
					"resource_type":"0",
					"sale_type":"pay",
					"setting_pannel_not_show":"false",
					"size":"L",
					"sortable":"true"
				},
				"items":[
					{
						"item_id":0,
						"name":"[绯色下午茶_Hi]",
						"properties":{
							"image":"https://i0.hdslb.com/bfs/garb/ed994898a23272f974cb2bdd7ca2c0d813f42fb8.png",
							"sale_type":"pay"
						}
					},
					{
						"item_id":0,
						"name":"[绯色下午茶_不乘]",
						"properties":{
							"image":"https://i0.hdslb.com/bfs/garb/d4f597f4277a8ccebcbac0c1926da977cd9d7c27.png",
							"sale_type":"pay"
						}
					},
					{
						"item_id":0,
						"name":"[绯色下午茶_不懂]",
						"properties":{
							"image":"https://i0.hdslb.com/bfs/garb/cf2f589278c2af4b5533e4e3e9c9ec564ee3e160.png",
							"sale_type":"pay"
						}
					},
					{
						"item_id":0,
						"name":"[绯色下午茶_中]",
						"properties":{
							"image":"https://i0.hdslb.com/bfs/garb/e18037706193234be7a159fa7fce19f8ceaf0149.png",
							"sale_type":"pay"
						}
					},
					{
						"item_id":0,
						"name":"[绯色下午茶_先走咯]",
						"properties":{
							"image":"https://i0.hdslb.com/bfs/garb/150661c0a7aee1a5cfff01a7e121171f824dd93d.png",
							"sale_type":"pay"
						}
					},
					{
						"item_id":0,
						"name":"[绯色下午茶_叫我吗]",
						"properties":{
							"image":"https://i0.hdslb.com/bfs/garb/9880537d42433a3acf28b3119acc859c3275ad42.png",
							"sale_type":"pay"
						}
					},
					{
						"item_id":0,
						"name":"[绯色下午茶_哭着跑走]",
						"properties":{
							"image":"https://i0.hdslb.com/bfs/garb/0587a3de60caca49e66ac74fe247cda395e64f6a.png",
							"sale_type":"pay"
						}
					},
					{
						"item_id":0,
						"name":"[绯色下午茶_喜欢]",
						"properties":{
							"image":"https://i0.hdslb.com/bfs/garb/f4fea1f353805dc6eed0de40d06dc4997ac1aa3a.png",
							"sale_type":"pay"
						}
					},
					{
						"item_id":0,
						"name":"[绯色下午茶_够了]",
						"properties":{
							"image":"https://i0.hdslb.com/bfs/garb/b6706e87261d49c37c093ab2d94d899d37a1fd48.png",
							"sale_type":"pay"
						}
					},
					{
						"item_id":0,
						"name":"[绯色下午茶_好吃]",
						"properties":{
							"image":"https://i0.hdslb.com/bfs/garb/4f4eb9519f03487195adeb52af83a7234cc3a4b9.png",
							"sale_type":"pay"
						}
					},
					{
						"item_id":0,
						"name":"[绯色下午茶_恁咋不早说]",
						"properties":{
							"image":"https://i0.hdslb.com/bfs/garb/514de3c8e8af894df402858a0a822a0739dd617b.png",
							"sale_type":"pay"
						}
					},
					{
						"item_id":0,
						"name":"[绯色下午茶_我给你等着]",
						"properties":{
							"image":"https://i0.hdslb.com/bfs/garb/f982d006ce3ae6e82112b7da26e0dc5d7d036311.png",
							"sale_type":"pay"
						}
					},
					{
						"item_id":0,
						"name":"[绯色下午茶_撒泼]",
						"properties":{
							"image":"https://i0.hdslb.com/bfs/garb/57335c0718f443d8a90c8bfc743f7555cbcc181d.png",
							"sale_type":"pay"
						}
					},
					{
						"item_id":0,
						"name":"[绯色下午茶_激动]",
						"properties":{
							"image":"https://i0.hdslb.com/bfs/garb/3def99fd8a9bc57a4209ada8bbde4e56177acc2d.png",
							"sale_type":"pay"
						}
					},
					{
						"item_id":0,
						"name":"[绯色下午茶_绅士]",
						"properties":{
							"image":"https://i0.hdslb.com/bfs/garb/2e7d14313b878be5d6258a01f2082031d120c134.png",
							"sale_type":"pay"
						}
					}
				]
			}
		],
		"skin":[
			{
				"item_id":1755569308001,
				"name":"绯色下午茶",
				"suit_item_id":323130601,
				"properties":{
					"color":"#000000",
					"color_mode":"light",
					"color_second_page":"#FFFFFF",
					"goods_type":"suit",
					"head_bg":"https://i0.hdslb.com/bfs/garb/f520e1a7d43a74a8876527b1b9cde56a1ff332f6.png",
					"head_myself_mp4_bg":"",
					"head_myself_mp4_play":"loop",
					"head_myself_squared_bg":"https://i0.hdslb.com/bfs/garb/63dd042f3e82045cc765950c7652a6dca8df8e2f.jpg",
					"head_tab_bg":"https://i0.hdslb.com/bfs/baselabs/op/0a79ac6c287ad02fb6a7ac51fad9bf0e165b5d5578c7ef83cc03bdc9868e5ed1.png",
					"image_cover":"https://i0.hdslb.com/bfs/garb/36068f27011b4dab8387a1c4d0acdc00d1c00b01.jpg",
					"image_preview":"https://i0.hdslb.com/bfs/garb/36068f27011b4dab8387a1c4d0acdc00d1c00b01.jpg",
					"package_md5":"0cf409a53833beb4fcfd9979fa89cc78",
					"package_url":"https://i0.hdslb.com/bfs/garb/zip/9eca3f0d4e94194893562462447ff591c9840c23.zip",
					"tail_bg":"https://i0.hdslb.com/bfs/garb/33a505a0ba67048aa121a86d750661c094d78c78.png",
					"tail_color":"#878787",
					"tail_color_selected":"#D35E51",
					"tail_icon_channel":"https://i0.hdslb.com/bfs/garb/2ef06cab89b3c38aa66ff64d512619a0fa764fca.png",
					"tail_icon_dynamic":"https://i0.hdslb.com/bfs/garb/2ef06cab89b3c38aa66ff64d512619a0fa764fca.png",
					"tail_icon_main":"https://i0.hdslb.com/bfs/garb/dbe9d512b49e9e9701e8a1c411eb28d0791b53cb.png",
					"tail_icon_mode":"img",
					"tail_icon_myself":"https://i0.hdslb.com/bfs/garb/b00c6204d197647777387ac87942d4d498abbc38.png",
					"tail_icon_pub_btn_bg":"https://i0.hdslb.com/bfs/garb/911eeee2eb52e37aff427a60ae96fef8714f7b12.png",
					"tail_icon_selected_channel":"https://i0.hdslb.com/bfs/garb/1fb10dc0eb29119789f727952e39ded2c1f1e8b8.png",
					"tail_icon_selected_dynamic":"https://i0.hdslb.com/bfs/garb/1fb10dc0eb29119789f727952e39ded2c1f1e8b8.png",
					"tail_icon_selected_main":"https://i0.hdslb.com/bfs/garb/11cc7352e4abd0c23b30b10fa4155cfb89541419.png",
					"tail_icon_selected_myself":"https://i0.hdslb.com/bfs/garb/0104360e62a79ba326460af45acfc1ae30176307.png",
					"tail_icon_selected_pub_btn_bg":"https://i0.hdslb.com/bfs/garb/911eeee2eb52e37aff427a60ae96fef8714f7b12.png",
					"tail_icon_selected_shop":"https://i0.hdslb.com/bfs/garb/c31d1fb14450a9c3c6c46d88a95b4658246865f1.png",
					"tail_icon_shop":"https://i0.hdslb.com/bfs/garb/4c6079b109cc431ae2b96bdd66b8f3a8dbe75a9d.png",
					"ver":"1755826452"
				}
			}
		],
		"space_bg":[
			{
				"item_id":1755569056001,
				"name":"绯色下午茶",
				"suit_item_id":323130601,
				"properties":{
					"fan_no_color":"#ffffff",
					"goods_type":"suit",
					"image1_landscape":"https://i0.hdslb.com/bfs/garb/ad53c399aafacfc1a1ce20a245e964cefb81249a.jpg",
					"image1_portrait":"https://i0.hdslb.com/bfs/garb/f74dc3522e985a2d84ab83c19e77ac4539bd4612.jpg"
				}
			}
		]
	},
	"fan_user":{
		"mid":3493131766991076,
		"nickname":"达众科技"
	}
}