{
	"item_id":35524,
	"name":"君有云",
	"group_id":8,
	"group_name":"君有云",
	"part_id":5,
	"properties":{
		"addable":"true",
		"biz":"dynamic,reply,watch_full",
		"image":"https://i0.hdslb.com/bfs/emote/fdf059355530ddb8482d3af7eb3268ebf7489be6.png",
		"is_symbol":"false",
		"item_ids":"35523,35525,35526,35527,35528,35529,35530,35531,35532,35533",
		"permanent":"false",
		"preview":"false",
		"realname_auth":"false",
		"recently_used":"false",
		"recommend":"false",
		"removable":"true",
		"sale_type":"pay",
		"setting_pannel_not_show":"false",
		"size":"L",
		"sortable":"true"
	},
	"suit_items":{
		"emoji":[
			{
				"item_id":35523,
				"name":"[君有云_安慰]",
				"tab_id":7,
				"properties":{
					"associate":"false",
					"image":"https://i0.hdslb.com/bfs/emote/3e41e546673636189ab0cf0e071ef7a94e8f081f.png",
					"is_symbol":"false",
					"sale_type":"pay"
				}
			},
			{
				"item_id":35525,
				"name":"[君有云_傲娇]",
				"tab_id":7,
				"properties":{
					"associate":"false",
					"image":"https://i0.hdslb.com/bfs/emote/a50fba63f6eb717f7957fb73deae03160386a803.png",
					"is_symbol":"false",
					"sale_type":"pay"
				}
			},
			{
				"item_id":35526,
				"name":"[君有云_吃瓜]",
				"tab_id":7,
				"properties":{
					"associate":"false",
					"image":"https://i0.hdslb.com/bfs/emote/b6883805b654489e0eed94dcb3bfbbd807467ea8.png",
					"is_symbol":"false",
					"sale_type":"pay"
				}
			},
			{
				"item_id":35527,
				"name":"[君有云_沮丧]",
				"tab_id":7,
				"properties":{
					"associate":"false",
					"image":"https://i0.hdslb.com/bfs/emote/3e44beda2020bf9ea2a95f30313ec60b01d23079.png",
					"is_symbol":"false",
					"sale_type":"pay"
				}
			},
			{
				"item_id":35528,
				"name":"[君有云_看书]",
				"tab_id":7,
				"properties":{
					"associate":"false",
					"image":"https://i0.hdslb.com/bfs/emote/82aa987821901ca838f2a13a54e5cbcb253b3066.png",
					"is_symbol":"false",
					"sale_type":"pay"
				}
			},
			{
				"item_id":35529,
				"name":"[君有云_让我康康]",
				"tab_id":7,
				"properties":{
					"associate":"false",
					"image":"https://i0.hdslb.com/bfs/emote/2a18bca2cdba271706a2425735a8ba99798ea4e3.png",
					"is_symbol":"false",
					"sale_type":"pay"
				}
			},
			{
				"item_id":35530,
				"name":"[君有云_生气]",
				"tab_id":7,
				"properties":{
					"associate":"false",
					"image":"https://i0.hdslb.com/bfs/emote/06d066a38c78467d3a49b8b1ea3094462f88cd97.png",
					"is_symbol":"false",
					"sale_type":"pay"
				}
			},
			{
				"item_id":35531,
				"name":"[君有云_师姐救我]",
				"tab_id":7,
				"properties":{
					"associate":"false",
					"image":"https://i0.hdslb.com/bfs/emote/9868a328abcf3b054e1505eb5d1873ea8a95be8d.png",
					"is_symbol":"false",
					"sale_type":"pay"
				}
			},
			{
				"item_id":35532,
				"name":"[君有云_捅回去]",
				"tab_id":7,
				"properties":{
					"associate":"false",
					"image":"https://i0.hdslb.com/bfs/emote/7569bcb485c0c1450061e3de6c060c06bf2c0412.png",
					"is_symbol":"false",
					"sale_type":"pay"
				}
			},
			{
				"item_id":35533,
				"name":"[君有云_捅你]",
				"tab_id":7,
				"properties":{
					"associate":"false",
					"image":"https://i0.hdslb.com/bfs/emote/6b81bb6bc282c8d2d86d80079e5e4e08e693907c.png",
					"is_symbol":"false",
					"sale_type":"pay"
				}
			}
		]
	}
}