{
	"item_id":36095,
	"name":"伍六七",
	"group_id":8,
	"group_name":"伍六七",
	"part_id":5,
	"properties":{
		"addable":"true",
		"biz":"dynamic,reply,watch_full",
		"image":"https://i0.hdslb.com/bfs/emote/37d965fbf60c797f741904447c7f922256befa59.png",
		"is_symbol":"false",
		"item_ids":"36085,36086,36087,36088,36089,36090,36091,36092,36093,36094",
		"permanent":"false",
		"preview":"false",
		"realname_auth":"false",
		"recently_used":"false",
		"recommend":"false",
		"removable":"true",
		"sale_type":"pay",
		"setting_pannel_not_show":"false",
		"size":"L",
		"sortable":"true"
	},
	"suit_items":{
		"emoji":[
			{
				"item_id":36085,
				"name":"[伍六七_傲娇]",
				"tab_id":7,
				"properties":{
					"associate":"false",
					"image":"https://i0.hdslb.com/bfs/emote/1809cbe2a18a86d96bb5a63675fc504e60eb5ece.png",
					"is_symbol":"false",
					"sale_type":"pay"
				}
			},
			{
				"item_id":36086,
				"name":"[伍六七_点赞]",
				"tab_id":7,
				"properties":{
					"associate":"false",
					"image":"https://i0.hdslb.com/bfs/emote/cefe1c6857c92267f5b68aa90e40794546d8dc76.png",
					"is_symbol":"false",
					"sale_type":"pay"
				}
			},
			{
				"item_id":36087,
				"name":"[伍六七_干杯]",
				"tab_id":7,
				"properties":{
					"associate":"false",
					"image":"https://i0.hdslb.com/bfs/emote/328709588ae4cc07b5123e0fa486b056a799b397.png",
					"is_symbol":"false",
					"sale_type":"pay"
				}
			},
			{
				"item_id":36088,
				"name":"[伍六七_惊吓]",
				"tab_id":7,
				"properties":{
					"associate":"false",
					"image":"https://i0.hdslb.com/bfs/emote/41e804c00bc7bc729672f41a971a3702a22cb80a.png",
					"is_symbol":"false",
					"sale_type":"pay"
				}
			},
			{
				"item_id":36089,
				"name":"[伍六七_可怜]",
				"tab_id":7,
				"properties":{
					"associate":"false",
					"image":"https://i0.hdslb.com/bfs/emote/6071b2cdecda87c6deb735e861bac3db83aacaeb.png",
					"is_symbol":"false",
					"sale_type":"pay"
				}
			},
			{
				"item_id":36090,
				"name":"[伍六七_生气]",
				"tab_id":7,
				"properties":{
					"associate":"false",
					"image":"https://i0.hdslb.com/bfs/emote/ce73aa7f5d463369b473e76d245fb9e5101cde0e.png",
					"is_symbol":"false",
					"sale_type":"pay"
				}
			},
			{
				"item_id":36091,
				"name":"[伍六七_投币]",
				"tab_id":7,
				"properties":{
					"associate":"false",
					"image":"https://i0.hdslb.com/bfs/emote/8ccba0af19276863f815898753caba29ff2c5fe3.png",
					"is_symbol":"false",
					"sale_type":"pay"
				}
			},
			{
				"item_id":36092,
				"name":"[伍六七_嫌弃]",
				"tab_id":7,
				"properties":{
					"associate":"false",
					"image":"https://i0.hdslb.com/bfs/emote/5cd1923c7787879d59f8f01a626fc2483b48c16c.png",
					"is_symbol":"false",
					"sale_type":"pay"
				}
			},
			{
				"item_id":36093,
				"name":"[伍六七_虚脱]",
				"tab_id":7,
				"properties":{
					"associate":"false",
					"image":"https://i0.hdslb.com/bfs/emote/145ed06de9e2c5685dd06f67d29009dd282ce1a7.png",
					"is_symbol":"false",
					"sale_type":"pay"
				}
			},
			{
				"item_id":36094,
				"name":"[伍六七_疑惑]",
				"tab_id":7,
				"properties":{
					"associate":"false",
					"image":"https://i0.hdslb.com/bfs/emote/ce085c1c1e061cccb9c9859d5fce1cee018df87a.png",
					"is_symbol":"false",
					"sale_type":"pay"
				}
			}
		]
	}
}